<?xml version="1.1" encoding="UTF-8"?>

<!--
 * See the NOTICE file distributed with this work for additional
 * information regarding copyright ownership.
 *
 * This is free software; you can redistribute it and/or modify it
 * under the terms of the GNU Lesser General Public License as
 * published by the Free Software Foundation; either version 2.1 of
 * the License, or (at your option) any later version.
 *
 * This software is distributed in the hope that it will be useful,
 * but WITHOUT ANY WARRANTY; without even the implied warranty of
 * MERCHANTABILITY or FITNESS FOR A PARTICULAR PURPOSE. See the GNU
 * Lesser General Public License for more details.
 *
 * You should have received a copy of the GNU Lesser General Public
 * License along with this software; if not, write to the Free
 * Software Foundation, Inc., 51 Franklin St, Fifth Floor, Boston, MA
 * 02110-1301 USA, or see the FSF site: http://www.fsf.org.
-->

<xwikidoc version="1.5" reference="JIRA.JIRAAuth.BasicAuthConfigDisplayer" locale="">
  <web>JIRA.JIRAAuth</web>
  <name>BasicAuthConfigDisplayer</name>
  <language/>
  <defaultLanguage/>
  <translation>0</translation>
  <creator>xwiki:XWiki.Admin</creator>
  <parent>WebHome</parent>
  <author>xwiki:XWiki.Admin</author>
  <contentAuthor>xwiki:XWiki.Admin</contentAuthor>
  <version>1.1</version>
  <title/>
  <comment/>
  <minorEdit>false</minorEdit>
  <syntaxId>xwiki/2.1</syntaxId>
  <hidden>true</hidden>
  <content>{{velocity}}
#set ($basicAuthClass = 'JIRA.JIRAAuth.BasicAuthClass')
#set ($confDoc = $xwiki.getDocument('JIRA.JIRAAuth.BasicAuthConfiguration'))
#set ($discard = $confDoc.setHidden(true))
#set ($authors = $confDoc.document.getAuthors())
#set ($discard = $authors.setCreator($services.user.superAdminUserReference))
#set ($discard = $authors.setContentAuthor($services.user.superAdminUserReference))
#set ($discard = $authors.setEffectiveMetadataAuthor($services.user.superAdminUserReference))
#set ($discard = $authors.setOriginalMetadataAuthor($services.user.superAdminUserReference))
#set ($confObjects = $confDoc.getObjects($basicAuthClass))
#if ($xcontext.action == 'get')
  #if ($request.getParameter('save') == 'true')
    ## Save the changes
    #if ($services.csrf.isTokenValid($!request.form_token))
      #foreach ($obj in $confObjects)
        #set ($formIdFieldName = "${basicAuthClass}_${obj.number}_id")
        #set ($formUsernameFieldName = "${basicAuthClass}_${obj.number}_username")
        #set ($formPwdFieldName = "${basicAuthClass}_${obj.number}_password")
        #set ($formIdValue = $request.getParameter($formIdFieldName))
        #set ($formUsernameValue = $request.getParameter($formUsernameFieldName))
        #set ($formPwdValue = $request.getParameter($formPwdFieldName))
        #if ($formIdValue != $NULL &amp;&amp; $formUsernameValue != $NULL &amp;&amp; $formPwdValue != $NULL)
          #set ($discard = $obj.set('id', $formIdValue))
          #set ($discard = $obj.set('username', $formUsernameValue))
          #set ($discard = $obj.set('password', $formPwdValue))
        #else
          ## Seem that the object is not any more in the form, so drop it
          #set ($discard = $confDoc.removeObject($obj))
        #end
      #end
      #set ($discard = $confDoc.save())
    #else
      #set($discard = $response.setStatus(403))
      #jsonResponse({"error": "Invalid CSRF token"})
    #end
  #else
    ## Show the content
    #set ($configId = $request.id)
    #set ($confObj = $NULL)
    #foreach ($o in $confObjects)
      #if ($o.getValue('id') == $configId)
        #set ($confObj = $o)
      #end
    #end
    #if ($confObj == $NULL)
      #set ($confObj = $confDoc.newObject($basicAuthClass))
      #set ($discard = $confObj.set('id', $configId))
      #set ($discard = $confDoc.save())
    #end
    $confObj.display('id', 'hidden')

    {{html clean="false"}}
    &lt;dl&gt;
      &lt;dt&gt;
        &lt;label for="${basicAuthClass}_${confObj.number}_username"&gt;$services.localization.render('jira.config.auth.basicAuth.username', 'html/5.0')&lt;/label&gt;
      &lt;/dt&gt;
      &lt;dd&gt;
        {{/html}}

        $confObj.display('username', 'edit')

        {{html clean="false"}}
      &lt;/dd&gt;
      &lt;dt&gt;
        &lt;label for="${basicAuthClass}_${confObj.number}_password"&gt;$services.localization.render('jira.config.auth.basicAuth.password', 'html/5.0')&lt;/label&gt;
      &lt;/dt&gt;
      &lt;dd&gt;
        {{/html}}

        $confObj.display('password', 'edit')

        {{html clean="false"}}
      &lt;/dd&gt;
    &lt;/dl&gt;
    {{/html}}
  #end
#end
{{/velocity}}</content>
  <object>
    <name>JIRA.JIRAAuth.BasicAuthConfigDisplayer</name>
    <number>0</number>
    <className>XWiki.StyleSheetExtension</className>
    <guid>baf7fb7b-b7b2-4dc6-b46e-0b33ff2b6ca2</guid>
    <class>
      <name>XWiki.StyleSheetExtension</name>
      <customClass/>
      <customMapping/>
      <defaultViewSheet/>
      <defaultEditSheet/>
      <defaultWeb/>
      <nameField/>
      <validationScript/>
      <cache>
        <cache>0</cache>
        <defaultValue>long</defaultValue>
        <disabled>0</disabled>
        <displayType>select</displayType>
        <freeText>forbidden</freeText>
        <largeStorage>0</largeStorage>
        <multiSelect>0</multiSelect>
        <name>cache</name>
        <number>5</number>
        <prettyName>Caching policy</prettyName>
        <relationalStorage>0</relationalStorage>
        <separator> </separator>
        <separators>|, </separators>
        <size>1</size>
        <unmodifiable>0</unmodifiable>
        <values>long|short|default|forbid</values>
        <classType>com.xpn.xwiki.objects.classes.StaticListClass</classType>
      </cache>
      <code>
        <contenttype>PureText</contenttype>
        <disabled>0</disabled>
        <editor>PureText</editor>
        <name>code</name>
        <number>2</number>
        <prettyName>Code</prettyName>
        <restricted>0</restricted>
        <rows>20</rows>
        <size>50</size>
        <unmodifiable>0</unmodifiable>
        <classType>com.xpn.xwiki.objects.classes.TextAreaClass</classType>
      </code>
      <contentType>
        <cache>0</cache>
        <disabled>0</disabled>
        <displayType>select</displayType>
        <freeText>forbidden</freeText>
        <largeStorage>0</largeStorage>
        <multiSelect>0</multiSelect>
        <name>contentType</name>
        <number>6</number>
        <prettyName>Content Type</prettyName>
        <relationalStorage>0</relationalStorage>
        <separator> </separator>
        <separators>|, </separators>
        <size>1</size>
        <unmodifiable>0</unmodifiable>
        <values>CSS|LESS</values>
        <classType>com.xpn.xwiki.objects.classes.StaticListClass</classType>
      </contentType>
      <name>
        <disabled>0</disabled>
        <name>name</name>
        <number>1</number>
        <prettyName>Name</prettyName>
        <size>30</size>
        <unmodifiable>0</unmodifiable>
        <classType>com.xpn.xwiki.objects.classes.StringClass</classType>
      </name>
      <parse>
        <disabled>0</disabled>
        <displayFormType>select</displayFormType>
        <displayType>yesno</displayType>
        <name>parse</name>
        <number>4</number>
        <prettyName>Parse content</prettyName>
        <unmodifiable>0</unmodifiable>
        <classType>com.xpn.xwiki.objects.classes.BooleanClass</classType>
      </parse>
      <use>
        <cache>0</cache>
        <disabled>0</disabled>
        <displayType>select</displayType>
        <freeText>forbidden</freeText>
        <largeStorage>0</largeStorage>
        <multiSelect>0</multiSelect>
        <name>use</name>
        <number>3</number>
        <prettyName>Use this extension</prettyName>
        <relationalStorage>0</relationalStorage>
        <separator> </separator>
        <separators>|, </separators>
        <size>1</size>
        <unmodifiable>0</unmodifiable>
        <values>currentPage|onDemand|always</values>
        <classType>com.xpn.xwiki.objects.classes.StaticListClass</classType>
      </use>
    </class>
    <property>
      <cache>long</cache>
    </property>
    <property>
      <code>td.jira-auth-configuration dl {
        margin-left: 0px
}</code>
    </property>
    <property>
      <contentType>CSS</contentType>
    </property>
    <property>
      <name/>
    </property>
    <property>
      <parse>0</parse>
    </property>
    <property>
      <use>onDemand</use>
    </property>
  </object>
</xwikidoc>
